langrocks/app/server.py
langrocks/cli.py
langrocks/client/__init__.py
langrocks/client/cli.py
langrocks/client/code_runner.py
langrocks/client/computer.py
langrocks/client/files.py
langrocks/client/web_browser.py
langrocks/common/__init__.py
langrocks/common/display.py
langrocks/common/models/__init__.py
langrocks/common/models/computer.py
langrocks/common/models/files.py
langrocks/common/models/tools.proto
langrocks/common/models/tools_pb2.py
langrocks/common/models/tools_pb2_grpc.py
langrocks/common/models/web_browser.py
langrocks/common/provisioners/chroot.py
langrocks/common/websockify/__init__.py
langrocks/common/websockify/auth.py
langrocks/common/websockify/token.py
langrocks-0.2.2.dist-info/LICENSE
langrocks-0.2.2.dist-info/METADATA
langrocks-0.2.2.dist-info/WHEEL
langrocks-0.2.2.dist-info/entry_points.txt
langrocks-0.2.2.dist-info/RECORD
