Metadata-Version: 2.1
Name: langrocks
Version: 0.2.2
Summary: Tools like web browser and code interpreters for LLMs
License: MIT
Author: ajhai
Author-email: nitk.ajay@gmail.com
Requires-Python: >=3.10,<4
Classifier: License :: OSI Approved :: MIT License
Classifier: Programming Language :: Python :: 3
Classifier: Programming Language :: Python :: 3.10
Classifier: Programming Language :: Python :: 3.11
Classifier: Programming Language :: Python :: 3.12
Requires-Dist: pydantic (>=2.8.2,<3.0.0)
Requires-Dist: python-on-whales (>=0.73.0,<0.74.0)
